merle/__init__.py
merle/cli.py
merle/extractor.py
merle/fetched_resource.py
merle/url_parser.py
merle-0.0.1.dist-info/DESCRIPTION.rst
merle-0.0.1.dist-info/METADATA
merle-0.0.1.dist-info/RECORD
merle-0.0.1.dist-info/WHEEL
merle-0.0.1.dist-info/entry_points.txt
merle-0.0.1.dist-info/metadata.json
merle-0.0.1.dist-info/top_level.txt
