Metadata-Version: 2.0
Name: merle
Version: 0.0.1
Summary: Command-line tool for extracting metadata from URLs
Home-page: http://danwin.com
Author: Dan Nguyen
Author-email: dansonguyen@gmail.com
License: MIT
Platform: UNKNOWN
Classifier: Programming Language :: Python :: 3.4
Classifier: Environment :: Console
Classifier: Intended Audience :: Developers
Requires-Dist: merle
